Metadata-Version: 2.1
Name: mail-sender-1.0
Version: 1.0
Summary: Utility class for sending emails
Author: AdanEinstein
Author-email: adaneinstein@gmail.com
